setup.cfg
setup.py
gtin/__init__.py
gtin/validator.py
gtin/validator_test.py
gtin_validator.egg-info/PKG-INFO
gtin_validator.egg-info/SOURCES.txt
gtin_validator.egg-info/dependency_links.txt
gtin_validator.egg-info/entry_points.txt
gtin_validator.egg-info/top_level.txt