Metadata-Version: 1.1
Name: gtin-validator
Version: 1.0.2
Summary: Validator for Global Trade Item Numbers (GTIN)
Home-page: https://github.com/charithe/gtin-validator
Author: Charith Ellawala
Author-email: charith@lucidelectricdreams.com
License: Apache
Keywords: utilities
Platform: UNKNOWN
Classifier: Development Status :: 4 - Beta
Classifier: Intended Audience :: Developers
Classifier: Topic :: Utilities
Classifier: License :: OSI Approved :: Apache Software License
Classifier: Programming Language :: Python :: 2
Classifier: Programming Language :: Python :: 2.7
Classifier: Programming Language :: Python :: 3
